[
  {
    "domain": ".shopee.co.id",
    "expirationDate": 1762114670,
    "hostOnly": false,
    "httpOnly": false,
    "name": "_gcl_au",
    "path": "/",
    "sameSite": "unspecified",
    "secure": false,
    "session": false,
    "storeId": "0",
    "value": "1.1.1870901511.1754338671"
  },
  {
    "domain": ".shopee.co.id",
    "expirationDate": 1756930670,
    "hostOnly": false,
    "httpOnly": false,
    "name": "_med",
    "path": "/",
    "sameSite": "unspecified",
    "secure": false,
    "session": false,
    "storeId": "0",
    "value": "refer"
  },
  {
    "domain": "shopee.co.id",
    "hostOnly": true,
    "httpOnly": false,
    "name": "csrftoken",
    "path": "/",
    "sameSite": "unspecified",
    "secure": false,
    "session": true,
    "storeId": "0",
    "value": "68zBVD31mXKYSXE8bZEnDW7HMXw8b5kC"
  },
  {
    "domain": "shopee.co.id",
    "hostOnly": true,
    "httpOnly": false,
    "name": "_sapid",
    "path": "/",
    "sameSite": "unspecified",
    "secure": false,
    "session": true,
    "storeId": "0",
    "value": "af2df9d9c03868b1aa7035dbb553a38feee0b41404ca2994d3c4ff8a"
  },
  {
    "domain": ".shopee.co.id",
    "expirationDate": 1762158579,
    "hostOnly": false,
    "httpOnly": false,
    "name": "_fbp",
    "path": "/",
    "sameSite": "lax",
    "secure": false,
    "session": false,
    "storeId": "0",
    "value": "fb.2.1754338671684.518730864723014041"
  },
  {
    "domain": "shopee.co.id",
    "expirationDate": 1785874672,
    "hostOnly": true,
    "httpOnly": false,
    "name": "_QPWSDCXHZQA",
    "path": "/",
    "sameSite": "unspecified",
    "secure": false,
    "session": false,
    "storeId": "0",
    "value": "02b1a13a-ac0e-4a65-cd34-7ea6278a2d82"
  },
  {
    "domain": "shopee.co.id",
    "expirationDate": 1785918581,
    "hostOnly": true,
    "httpOnly": false,
    "name": "REC7iLP4Q",
    "path": "/",
    "sameSite": "unspecified",
    "secure": false,
    "session": false,
    "storeId": "0",
    "value": "33f81f11-19e8-48df-8098-dad33a25811d"
  },
  {
    "domain": ".shopee.co.id",
    "expirationDate": 1754469231.407145,
    "hostOnly": false,
    "httpOnly": true,
    "name": "SPC_SI",
    "path": "/",
    "sameSite": "unspecified",
    "secure": true,
    "session": false,
    "storeId": "0",
    "value": "GEB3aAAAAABLd094TEJMdoMSYgEAAAAASk52N01MSng="
  },
  {
    "domain": "shopee.co.id",
    "expirationDate": 1754425373.636655,
    "hostOnly": true,
    "httpOnly": true,
    "name": "SPC_SEC_SI",
    "path": "/",
    "sameSite": "unspecified",
    "secure": true,
    "session": false,
    "storeId": "0",
    "value": "v1-MGppTUJVckNZOTRIbkphTD3OdZJxfzF+CaVWFPZFj5LbUpPkrOa8tUBFYzei3cFOOhzv/xefdAJWRls6InvvZOfYsSQtCNFQji0PuF+vyZc="
  },
  {
    "domain": ".shopee.co.id",
    "expirationDate": 1788898674.213655,
    "hostOnly": false,
    "httpOnly": true,
    "name": "REC_T_ID",
    "path": "/",
    "sameSite": "unspecified",
    "secure": true,
    "session": false,
    "storeId": "0",
    "value": "1a0624cc-7170-11f0-b763-0a3b37a59c34"
  },
  {
    "domain": ".shopee.co.id",
    "expirationDate": 1788898674.213655,
    "hostOnly": false,
    "httpOnly": false,
    "name": "SPC_F",
    "path": "/",
    "sameSite": "unspecified",
    "secure": true,
    "session": false,
    "storeId": "0",
    "value": "NLFi671sz3gj93nugo8VN85qp8KyOtN1"
  },
  {
    "domain": ".shopee.co.id",
    "expirationDate": 1754468987,
    "hostOnly": false,
    "httpOnly": false,
    "name": "_gid",
    "path": "/",
    "sameSite": "unspecified",
    "secure": false,
    "session": false,
    "storeId": "0",
    "value": "GA1.3.912185753.1754338681"
  },
  {
    "domain": ".shopee.co.id",
    "expirationDate": 1788898697.08903,
    "hostOnly": false,
    "httpOnly": false,
    "name": "SPC_CLIENTID",
    "path": "/",
    "sameSite": "unspecified",
    "secure": false,
    "session": false,
    "storeId": "0",
    "value": "TkxGaTY3MXN6M2dquavzyhpkcngqdrdm"
  },
  {
    "domain": ".shopee.co.id",
    "expirationDate": 1788942831.406145,
    "hostOnly": false,
    "httpOnly": false,
    "name": "SPC_U",
    "path": "/",
    "sameSite": "unspecified",
    "secure": true,
    "session": false,
    "storeId": "0",
    "value": "1603331602"
  },
  {
    "domain": ".shopee.co.id",
    "expirationDate": 1788942831.407145,
    "hostOnly": false,
    "httpOnly": false,
    "name": "SPC_R_T_ID",
    "path": "/",
    "sameSite": "unspecified",
    "secure": true,
    "session": false,
    "storeId": "0",
    "value": "udU4GSmUi2DrEa/h5tM/ZZzu2tCosPqi1LvLUUUjEGGSbx7gMAFRQ+ezek4kN8uTTH//lzhZdyvt/JUAOkneDEO2ekY0/GwXU3425A+gmaKQ3WNm8xt4eeDo/ak35+JyjRdiMHmnLMO8wATaBIQPBVhd7cFyRwPOTQwldppZc2Y="
  },
  {
    "domain": ".shopee.co.id",
    "expirationDate": 1788942831.407145,
    "hostOnly": false,
    "httpOnly": false,
    "name": "SPC_R_T_IV",
    "path": "/",
    "sameSite": "unspecified",
    "secure": true,
    "session": false,
    "storeId": "0",
    "value": "Z1pFMENwMlI4emlLNWhWUA=="
  },
  {
    "domain": ".shopee.co.id",
    "expirationDate": 1788942831.407145,
    "hostOnly": false,
    "httpOnly": true,
    "name": "SPC_T_ID",
    "path": "/",
    "sameSite": "unspecified",
    "secure": true,
    "session": false,
    "storeId": "0",
    "value": "udU4GSmUi2DrEa/h5tM/ZZzu2tCosPqi1LvLUUUjEGGSbx7gMAFRQ+ezek4kN8uTTH//lzhZdyvt/JUAOkneDEO2ekY0/GwXU3425A+gmaKQ3WNm8xt4eeDo/ak35+JyjRdiMHmnLMO8wATaBIQPBVhd7cFyRwPOTQwldppZc2Y="
  },
  {
    "domain": ".shopee.co.id",
    "expirationDate": 1788942831.407145,
    "hostOnly": false,
    "httpOnly": true,
    "name": "SPC_T_IV",
    "path": "/",
    "sameSite": "unspecified",
    "secure": true,
    "session": false,
    "storeId": "0",
    "value": "Z1pFMENwMlI4emlLNWhWUA=="
  },
  {
    "domain": ".shopee.co.id",
    "hostOnly": false,
    "httpOnly": false,
    "name": "SPC_CDS_CHAT",
    "path": "/",
    "sameSite": "unspecified",
    "secure": false,
    "session": true,
    "storeId": "0",
    "value": "751b02c1-4c72-4196-8a80-7a715ae4b141"
  },
  {
    "domain": ".shopee.co.id",
    "expirationDate": 1788942831.406145,
    "hostOnly": false,
    "httpOnly": true,
    "name": "SPC_ST",
    "path": "/",
    "sameSite": "unspecified",
    "secure": true,
    "session": false,
    "storeId": "0",
    "value": ".dmZJYVlYZTl4WWt3SDFMOFFH3Z7Zc+Zt01SiMq2gvNL2X+r4YkEx2vg64KapMDt0h/it7aKAelqhIfUkp0xYZuE36cdwE+S048sFZzFMzLBEzJTKnl6pH+D4lDfaSHT8F6y+pzh79B1ByO4r4INpzcXcDeFphap+zRZKo7SsMg3zzPM1AnfUKXA7xBmVyDRANhcT2mrwDwGPwDwhDVgf0ruCJSLXsX0Y0EFcAb6wmCaTDRekLC8xn2/VVY+UEe5n"
  },
  {
    "domain": ".shopee.co.id",
    "expirationDate": 1754385535,
    "hostOnly": false,
    "httpOnly": false,
    "name": "AMP_TOKEN",
    "path": "/",
    "sameSite": "unspecified",
    "secure": false,
    "session": false,
    "storeId": "0",
    "value": "%24NOT_FOUND"
  },
  {
    "domain": "shopee.co.id",
    "expirationDate": 1785918584,
    "hostOnly": true,
    "httpOnly": false,
    "name": "shopee_webUnique_ccd",
    "path": "/",
    "sameSite": "unspecified",
    "secure": false,
    "session": false,
    "storeId": "0",
    "value": "YrbJBiuXb2KyUGeI5LAzuQ%3D%3D%7C6FGTTeR1KkpRJVymf5G6CFgWtYBcZZYWsqS36VOObiJrMiYGEsrlE3yc6oWzuOna7NdcrOS4Nnv5G%2B0%3D%7C4Ko4kOahS0TDeZnw%7C08%7C3"
  },
  {
    "domain": "shopee.co.id",
    "expirationDate": 1785918584,
    "hostOnly": true,
    "httpOnly": false,
    "name": "ds",
    "path": "/",
    "sameSite": "unspecified",
    "secure": false,
    "session": false,
    "storeId": "0",
    "value": "89cf331f72ca8d0390c784c05c170a14"
  },
  {
    "domain": ".shopee.co.id",
    "expirationDate": 1788942587.892693,
    "hostOnly": false,
    "httpOnly": false,
    "name": "_ga_SW6D8G0HXK",
    "path": "/",
    "sameSite": "unspecified",
    "secure": false,
    "session": false,
    "storeId": "0",
    "value": "GS2.1.s1754381934$o1$g1$t1754382587$j51$l0$h0"
  },
  {
    "domain": ".shopee.co.id",
    "expirationDate": 1788942587.959693,
    "hostOnly": false,
    "httpOnly": false,
    "name": "_ga",
    "path": "/",
    "sameSite": "unspecified",
    "secure": false,
    "session": false,
    "storeId": "0",
    "value": "GA1.3.324055498.1754381935"
  },
  {
    "domain": ".shopee.co.id",
    "expirationDate": 1788942831.406145,
    "hostOnly": false,
    "httpOnly": true,
    "name": "SPC_EC",
    "path": "/",
    "sameSite": "unspecified",
    "secure": true,
    "session": false,
    "storeId": "0",
    "value": ".UmVOMEpaeE1BVWxPdjI4ajPvT/Jy0BwbDCFjt9aVfSAsB6eWkTSMaATXZ0YxBm6+I5QnEI4B3MRQZSSS/sr9HlRq1LF6a3sTjxw79SzsLNrFV7vE1RQCW+lRSLVBIPDWllt5PfHgbcUMbfz0aCNxBpnqfschZlE0DVV3kZQUw3khKRSD9P37KV087R9nhM3/ImQrIIOBy+LN2hamgttza7ew6gBxpEX4zkZBlu01TJb8QF63A2+4cIiVU0us3FfD"
  }
]
